odoo/addons/fleet_vehicle_calendar_year/README.rst
odoo/addons/fleet_vehicle_calendar_year/__init__.py
odoo/addons/fleet_vehicle_calendar_year/__manifest__.py
odoo/addons/fleet_vehicle_calendar_year/i18n/es.po
odoo/addons/fleet_vehicle_calendar_year/i18n/fleet_vehicle_calendar_year.pot
odoo/addons/fleet_vehicle_calendar_year/i18n/it.po
odoo/addons/fleet_vehicle_calendar_year/i18n/pt_BR.po
odoo/addons/fleet_vehicle_calendar_year/i18n/sv.po
odoo/addons/fleet_vehicle_calendar_year/models/__init__.py
odoo/addons/fleet_vehicle_calendar_year/models/fleet_vehicle.py
odoo/addons/fleet_vehicle_calendar_year/readme/CONTRIBUTORS.md
odoo/addons/fleet_vehicle_calendar_year/readme/CREDITS.md
odoo/addons/fleet_vehicle_calendar_year/readme/DESCRIPTION.md
odoo/addons/fleet_vehicle_calendar_year/static/description/banner.png
odoo/addons/fleet_vehicle_calendar_year/static/description/icon.png
odoo/addons/fleet_vehicle_calendar_year/static/description/index.html
odoo/addons/fleet_vehicle_calendar_year/views/fleet_vehicle.xml
odoo_addon_fleet_vehicle_calendar_year-18.0.1.0.0.2.dist-info/METADATA
odoo_addon_fleet_vehicle_calendar_year-18.0.1.0.0.2.dist-info/WHEEL
odoo_addon_fleet_vehicle_calendar_year-18.0.1.0.0.2.dist-info/top_level.txt
odoo_addon_fleet_vehicle_calendar_year-18.0.1.0.0.2.dist-info/RECORD
