Metadata-Version: 2.1
Name: odoo-addon-fleet_vehicle_calendar_year
Version: 18.0.1.0.0.2
Requires-Python: >=3.10
Requires-Dist: odoo==18.0.*
Summary: This module extends the fleet management functionality. Allows the registration of the vehicle's calendar year.
Home-page: https://github.com/OCA/fleet
License: AGPL-3
Author: Escodoo,Odoo Community Association (OCA)
Author-email: support@odoo-community.org
Classifier: Programming Language :: Python
Classifier: Framework :: Odoo
Classifier: Framework :: Odoo :: 18.0
Classifier: License :: OSI Approved :: GNU Affero General Public License v3
